nodestream_plugin_gcp_asset_inventory/__init__.py
nodestream_plugin_gcp_asset_inventory/gcpAsset.yaml
nodestream_plugin_gcp_asset_inventory/gcpPolicy.yaml
nodestream_plugin_gcp_asset_inventory/gcp_asset/__init__.py
nodestream_plugin_gcp_asset_inventory/gcp_asset/gcp_asset_extractor.py
nodestream_plugin_gcp_asset_inventory/gcp_policy/__init__.py
nodestream_plugin_gcp_asset_inventory/gcp_policy/gcp_policy_extractor.py
nodestream_plugin_gcp_asset_inventory/plugin.py
nodestream_plugin_gcp_asset_inventory-0.1.5.dist-info/METADATA
nodestream_plugin_gcp_asset_inventory-0.1.5.dist-info/WHEEL
nodestream_plugin_gcp_asset_inventory-0.1.5.dist-info/entry_points.txt
nodestream_plugin_gcp_asset_inventory-0.1.5.dist-info/RECORD
